purecpp_oracledb/__init__.py
purecpp_oracledb/vectordb/__init__.py
purecpp_oracledb/vectordb/backend.py
purecpp_oracledb/vectordb/document.py
purecpp_oracledb/vectordb/exceptions.py
purecpp_oracledb/vectordb/registry.py
purecpp_oracledb/vectordb/types.py
purecpp_oracledb/vectordb/backends/__init__.py
purecpp_oracledb/vectordb/backends/oracle_backend.py
purecpp_oracledb/vectordb/wrappers/__init__.py
purecpp_oracledb/vectordb/wrappers/concurrent.py
purecpp_oracledb/vectordb/wrappers/metrics.py
purecpp_oracledb-0.1.0.dist-info/licenses/LICENSE
purecpp_oracledb-0.1.0.dist-info/METADATA
purecpp_oracledb-0.1.0.dist-info/WHEEL
purecpp_oracledb-0.1.0.dist-info/top_level.txt
purecpp_oracledb-0.1.0.dist-info/RECORD
