Metadata-Version: 2.4
Name: purecpp-oracledb
Version: 0.1.0
Summary: PureCPP OracleDB integration
Author-email: pureai <contato@pureai.com.br>
Maintainer-email: pureai <contato@pureai.com.br>
License-Expression: MIT
Requires-Python: >=3.9
License-File: LICENSE
Requires-Dist: oracledb>=2.1
Dynamic: license-file
